ptgraphql/__init__.py
ptgraphql/_version.py
ptgraphql/ptgraphql.py
ptgraphql/data/__init__.py
ptgraphql/data/wordlists/__init__.py
ptgraphql/data/wordlists/endpoints.txt
ptgraphql/helpers/__init__.py
ptgraphql/helpers/_thread_local_stdout.py
ptgraphql/helpers/helpers.py
ptgraphql/modules/__init__.py
ptgraphql/modules/cache_control.py
ptgraphql/modules/cors.py
ptgraphql/modules/graphiql.py
ptgraphql/modules/introspection.py
ptgraphql/modules/is_graphql.py
ptgraphql/modules/method_change.py
ptgraphql-0.0.7.dist-info/licenses/LICENSE
ptgraphql-0.0.7.dist-info/METADATA
ptgraphql-0.0.7.dist-info/WHEEL
ptgraphql-0.0.7.dist-info/entry_points.txt
ptgraphql-0.0.7.dist-info/top_level.txt
ptgraphql-0.0.7.dist-info/RECORD
